ceda_es_client/__init__.py
ceda_es_client/root-ca.pem
ceda_elasticsearch_client-1.0.0.dist-info/METADATA
ceda_elasticsearch_client-1.0.0.dist-info/WHEEL
ceda_elasticsearch_client-1.0.0.dist-info/top_level.txt
ceda_elasticsearch_client-1.0.0.dist-info/RECORD
